opentele/__init__.py
opentele/api.py
opentele/debug.py
opentele/devices.py
opentele/exception.py
opentele/utils.py
opentele/td/__init__.py
opentele/td/account.py
opentele/td/auth.py
opentele/td/configs.py
opentele/td/mtp.py
opentele/td/shared.py
opentele/td/storage.py
opentele/td/tdesktop.py
opentele/tl/__init__.py
opentele/tl/configs.py
opentele/tl/shared.py
opentele/tl/telethon.py
opentele_py313-1.15.2.dist-info/licenses/LICENSE
opentele_py313-1.15.2.dist-info/METADATA
opentele_py313-1.15.2.dist-info/WHEEL
opentele_py313-1.15.2.dist-info/top_level.txt
opentele_py313-1.15.2.dist-info/RECORD
