Metadata-Version: 2.4
Name: opentele-py313
Version: 1.15.2
Summary: A Python 3.13+ compatible fork of opentele - Telegram API Library for converting between tdata and telethon sessions.
Home-page: https://github.com/yourusername/opentele-py313
Author: Aleksey (fork maintainer)
Author-email: your.email@example.com
License: MIT
Keywords: tdata,tdesktop,telegram,telethon,opentele,python313
Classifier: License :: OSI Approved :: MIT License
Classifier: Operating System :: Microsoft :: Windows
Classifier: Operating System :: MacOS
Classifier: Operating System :: POSIX :: Linux
Classifier: Programming Language :: Python :: 3
Classifier: Programming Language :: Python :: 3.7
Classifier: Programming Language :: Python :: 3.13
Classifier: Development Status :: 5 - Production/Stable
License-File: LICENSE
Requires-Dist: pyqt5
Requires-Dist: telethon
Requires-Dist: tgcrypto
Dynamic: author
Dynamic: author-email
Dynamic: classifier
Dynamic: description
Dynamic: description-content-type
Dynamic: home-page
Dynamic: keywords
Dynamic: license
Dynamic: license-file
Dynamic: requires-dist
Dynamic: summary
